sagikoza/__init__.py
sagikoza/core.py
sagikoza/normalize.py
sagikoza/parser/__init__.py
sagikoza/parser/pubs_basic_frame.py
sagikoza/parser/pubs_dispatcher.py
sagikoza/parser/pubstype_detail.py
sagikoza/parser/sel_pubs.py
sagikoza-2.3.1.dist-info/licenses/LICENSE
sagikoza-2.3.1.dist-info/METADATA
sagikoza-2.3.1.dist-info/WHEEL
sagikoza-2.3.1.dist-info/top_level.txt
sagikoza-2.3.1.dist-info/RECORD
