Metadata-Version: 2.4
Name: sagikoza
Version: 2.3.1
Summary: A Python library for crawling and retrieving all notices published under Japan’s Furikome Sagi Relief Act, with support for both full data extraction and incremental updates.
Home-page: https://github.com/new-village/sagikoza
Author: new-village
License: Apache License
Requires-Python: >=3.8
License-File: LICENSE
Requires-Dist: requests
Requires-Dist: beautifulsoup4
Requires-Dist: jpdatetime
Dynamic: home-page
Dynamic: license-file
Dynamic: requires-python
